multi_broker_sdk/__init__.py
multi_broker_sdk/brokers/__init__.py
multi_broker_sdk/brokers/base.py
multi_broker_sdk/brokers/exceptions.py
multi_broker_sdk/brokers/utils.py
multi_broker_sdk/brokers/providers/__init__.py
multi_broker_sdk/brokers/providers/fyers.py
multi_broker_sdk/brokers/tokens/__init__.py
multi_broker_sdk-0.1.1.dist-info/METADATA
multi_broker_sdk-0.1.1.dist-info/WHEEL
multi_broker_sdk-0.1.1.dist-info/top_level.txt
multi_broker_sdk-0.1.1.dist-info/RECORD
