Metadata-Version: 2.4
Name: multi-broker-sdk
Version: 0.1.1
Summary: Unified Python SDK for multiple stock broker APIs authentication.
Author-email: Dharmik Anghan <dharmikanghan09@gmail.com>
Maintainer-email: Dharmik Anghan <dharmikanghan09@gmail.com>
License: MIT
Keywords: stock,trading,broker,api,fyers
Classifier: Development Status :: 3 - Alpha
Classifier: Intended Audience :: Developers
Classifier: Intended Audience :: Financial and Insurance Industry
Classifier: License :: OSI Approved :: MIT License
Classifier: Operating System :: OS Independent
Classifier: Programming Language :: Python :: 3
Classifier: Programming Language :: Python :: 3.9
Classifier: Programming Language :: Python :: 3.10
Classifier: Programming Language :: Python :: 3.11
Classifier: Programming Language :: Python :: 3.12
Classifier: Topic :: Office/Business :: Financial :: Investment
Classifier: Topic :: Software Development :: Libraries :: Python Modules
Requires-Python: >=3.9
Requires-Dist: fyers_apiv3>=3.1.7
Requires-Dist: pyotp>=2.9.0
Requires-Dist: python-dotenv>=1.1.1
Requires-Dist: requests>=2.31.0
Requires-Dist: typing_extensions>=4.15.0
Requires-Dist: cryptography>=41.0.0
